<?xml version="1.0" encoding="UTF-8" ?>
<!DOCTYPE group PUBLIC "-//ESL/DTD eGauge 1.0//EN" "http://www.egauge.net/DTD/egauge-hist.dtd">
<group serial="0x59424923">
<data columns="2" time_stamp="0x5726c634" time_delta="3600" epoch="0x56d621fc">
 <cname t="P">Meadows West 3rd Floor</cname>
 <cname t="P">Meadows East 3rd Floor</cname>
 <r><c>2090412023</c><c>8309254624</c></r>
 <r><c>2082844022</c><c>8305040360</c></r>
 <r><c>2075391777</c><c>8301435912</c></r>
 <r><c>2069360481</c><c>8298287380</c></r>
 <r><c>2062968301</c><c>8295055506</c></r>
 <r><c>2056849714</c><c>8292327837</c></r>
 <r><c>2050599030</c><c>8288784123</c></r>
 <r><c>2044417881</c><c>8284983381</c></r>
 <r><c>2038647980</c><c>8281411786</c></r>
 <r><c>2033867010</c><c>8278820199</c></r>
 <r><c>2028282908</c><c>8275668845</c></r>
 <r><c>2023534432</c><c>8273128403</c></r>
 <r><c>2019064308</c><c>8270579114</c></r>
 <r><c>2014572445</c><c>8268037414</c></r>
 <r><c>2009887924</c><c>8266134223</c></r>
 <r><c>2005162414</c><c>8264115052</c></r>
 <r><c>2001034529</c><c>8261936848</c></r>
 <r><c>1996586644</c><c>8259287562</c></r>
 <r><c>1992376135</c><c>8256616253</c></r>
 <r><c>1987986162</c><c>8253478975</c></r>
 <r><c>1983469738</c><c>8250592931</c></r>
 <r><c>1978133272</c><c>8246965101</c></r>
 <r><c>1973185645</c><c>8243345428</c></r>
 <r><c>1966793543</c><c>8239135024</c></r>
 <r><c>1960487648</c><c>8235212722</c></r>
 <r><c>1953651161</c><c>8231586771</c></r>
 <r><c>1946683739</c><c>8228035084</c></r>
 <r><c>1939108702</c><c>8224515127</c></r>
 <r><c>1932992621</c><c>8221289843</c></r>
 <r><c>1927873458</c><c>8218763638</c></r>
 <r><c>1922228040</c><c>8215795096</c></r>
 <r><c>1916870124</c><c>8212913381</c></r>
 <r><c>1911344093</c><c>8210245684</c></r>
 <r><c>1906109473</c><c>8208042406</c></r>
 <r><c>1900813195</c><c>8205630171</c></r>
 <r><c>1896168219</c><c>8203955060</c></r>
 <r><c>1890987388</c><c>8201292093</c></r>
 <r><c>1886654080</c><c>8198468050</c></r>
 <r><c>1883020257</c><c>8196246608</c></r>
 <r><c>1879837524</c><c>8193981845</c></r>
 <r><c>1876530501</c><c>8191662191</c></r>
 <r><c>1872993676</c><c>8189026544</c></r>
 <r><c>1869463382</c><c>8187022786</c></r>
 <r><c>1864854561</c><c>8184292539</c></r>
 <r><c>1860279600</c><c>8181608886</c></r>
 <r><c>1854924038</c><c>8178499367</c></r>
 <r><c>1849424376</c><c>8176141354</c></r>
 <r><c>1842999843</c><c>8172392488</c></r>
 <r><c>1836425407</c><c>8169274914</c></r>
 <r><c>1829826717</c><c>8166472621</c></r>
 <r><c>1823353458</c><c>8163910333</c></r>
 <r><c>1816969755</c><c>8161702940</c></r>
 <r><c>1810610899</c><c>8158878551</c></r>
 <r><c>1805430671</c><c>8156275342</c></r>
 <r><c>1800402074</c><c>8152973022</c></r>
 <r><c>1795401477</c><c>8150784731</c></r>
 <r><c>1790074511</c><c>8147879739</c></r>
 <r><c>1784477931</c><c>8145054765</c></r>
 <r><c>1777607005</c><c>8141204296</c></r>
 <r><c>1771932999</c><c>8136946816</c></r>
 <r><c>1767403067</c><c>8132595885</c></r>
 <r><c>1762977752</c><c>8128916726</c></r>
 <r><c>1758680422</c><c>8126601856</c></r>
 <r><c>1754213441</c><c>8123606379</c></r>
 <r><c>1750561671</c><c>8121162243</c></r>
 <r><c>1746290485</c><c>8118502209</c></r>
 <r><c>1742066640</c><c>8116292209</c></r>
 <r><c>1737027908</c><c>8114128562</c></r>
 <r><c>1731376072</c><c>8111815619</c></r>
 <r><c>1726100752</c><c>8109612402</c></r>
 <r><c>1719918183</c><c>8106497089</c></r>
 <r><c>1713679300</c><c>8103171928</c></r>
 <r><c>1706723684</c><c>8099480922</c></r>
 <r><c>1699898898</c><c>8097638554</c></r>
 <r><c>1692710036</c><c>8094756928</c></r>
 <r><c>1686333400</c><c>8091616023</c></r>
 <r><c>1680157207</c><c>8088243685</c></r>
 <r><c>1674641524</c><c>8085779867</c></r>
 <r><c>1669037184</c><c>8082342618</c></r>
 <r><c>1662969712</c><c>8078835619</c></r>
 <r><c>1656736183</c><c>8075641359</c></r>
 <r><c>1652021009</c><c>8072688350</c></r>
 <r><c>1647150149</c><c>8069560040</c></r>
 <r><c>1642313301</c><c>8066271683</c></r>
 <r><c>1637166557</c><c>8062948574</c></r>
 <r><c>1632364567</c><c>8060104279</c></r>
 <r><c>1627897504</c><c>8057511569</c></r>
 <r><c>1622597996</c><c>8055042710</c></r>
 <r><c>1618353780</c><c>8052641345</c></r>
 <r><c>1614308706</c><c>8050691174</c></r>
 <r><c>1610177283</c><c>8048715220</c></r>
 <r><c>1605565860</c><c>8046619616</c></r>
 <r><c>1600226526</c><c>8044593881</c></r>
 <r><c>1594940777</c><c>8042066124</c></r>
 <r><c>1589343751</c><c>8038990581</c></r>
 <r><c>1584105112</c><c>8035788321</c></r>
 <r><c>1577971341</c><c>8031571354</c></r>
 <r><c>1571788967</c><c>8027105697</c></r>
 <r><c>1565065571</c><c>8023439117</c></r>
 <r><c>1559121756</c><c>8019961302</c></r>
 <r><c>1553084493</c><c>8016649624</c></r>
 <r><c>1547387366</c><c>8013482162</c></r>
 <r><c>1542155885</c><c>8010119137</c></r>
 <r><c>1536013067</c><c>8005747393</c></r>
 <r><c>1531554791</c><c>8001962594</c></r>
 <r><c>1526190928</c><c>7997947972</c></r>
 <r><c>1521044700</c><c>7994120532</c></r>
 <r><c>1515677218</c><c>7990849222</c></r>
 <r><c>1511166176</c><c>7987669488</c></r>
 <r><c>1505929314</c><c>7984298336</c></r>
 <r><c>1501460327</c><c>7981538784</c></r>
 <r><c>1496664611</c><c>7979302222</c></r>
 <r><c>1492252859</c><c>7977165602</c></r>
 <r><c>1488170325</c><c>7974974761</c></r>
 <r><c>1484270824</c><c>7973548496</c></r>
 <r><c>1479839765</c><c>7971800778</c></r>
 <r><c>1475220374</c><c>7970169025</c></r>
 <r><c>1469605418</c><c>7968160274</c></r>
 <r><c>1463574882</c><c>7965811462</c></r>
 <r><c>1457051939</c><c>7962891881</c></r>
 <r><c>1449837331</c><c>7959372210</c></r>
 <r><c>1443289091</c><c>7956501279</c></r>
 <r><c>1437018397</c><c>7953392209</c></r>
 <r><c>1430891263</c><c>7949896157</c></r>
 <r><c>1424832095</c><c>7946390363</c></r>
 <r><c>1419111841</c><c>7942618424</c></r>
 <r><c>1414846738</c><c>7940136884</c></r>
 <r><c>1410373087</c><c>7937377519</c></r>
 <r><c>1405937931</c><c>7934823935</c></r>
 <r><c>1401588640</c><c>7932486052</c></r>
 <r><c>1397313509</c><c>7930584939</c></r>
 <r><c>1392709894</c><c>7927836636</c></r>
 <r><c>1389114189</c><c>7924842949</c></r>
 <r><c>1384465788</c><c>7921547677</c></r>
 <r><c>1380419383</c><c>7919400968</c></r>
 <r><c>1375264513</c><c>7917177242</c></r>
 <r><c>1371849806</c><c>7915191167</c></r>
 <r><c>1368358588</c><c>7913146613</c></r>
 <r><c>1364799201</c><c>7911170327</c></r>
 <r><c>1361079733</c><c>7909130291</c></r>
 <r><c>1356866458</c><c>7907068078</c></r>
 <r><c>1352604762</c><c>7904695207</c></r>
 <r><c>1348349772</c><c>7901998602</c></r>
 <r><c>1343023455</c><c>7899293316</c></r>
 <r><c>1337735943</c><c>7895604022</c></r>
 <r><c>1332656310</c><c>7892296987</c></r>
 <r><c>1327292112</c><c>7888589040</c></r>
 <r><c>1322501981</c><c>7885870937</c></r>
 <r><c>1316000388</c><c>7883585461</c></r>
 <r><c>1311250664</c><c>7881865527</c></r>
 <r><c>1306080398</c><c>7879238059</c></r>
 <r><c>1300822743</c><c>7876449312</c></r>
 <r><c>1295688567</c><c>7874281097</c></r>
 <r><c>1291848008</c><c>7872464787</c></r>
 <r><c>1287267947</c><c>7870557281</c></r>
 <r><c>1282932564</c><c>7868205107</c></r>
 <r><c>1277809110</c><c>7865377673</c></r>
 <r><c>1272404044</c><c>7862329307</c></r>
 <r><c>1268238955</c><c>7859948390</c></r>
 <r><c>1263598164</c><c>7857899973</c></r>
 <r><c>1259444735</c><c>7855530631</c></r>
 <r><c>1255419592</c><c>7853573501</c></r>
 <r><c>1251110702</c><c>7851482255</c></r>
 <r><c>1246062066</c><c>7849276784</c></r>
 <r><c>1241026307</c><c>7846891939</c></r>
 <r><c>1235140622</c><c>7844012456</c></r>
 <r><c>1229224090</c><c>7841128474</c></r>
 <r><c>1222633467</c><c>7837066192</c></r>
 <r><c>1215740769</c><c>7833920342</c></r>
 <r><c>1209282977</c><c>7829247587</c></r>
 <r><c>1203054760</c><c>7825128819</c></r>
 <r><c>1197093562</c><c>7821161025</c></r>
 <r><c>1191552356</c><c>7817843901</c></r>
 <r><c>1186573806</c><c>7815237129</c></r>
 <r><c>1181702938</c><c>7812508642</c></r>
 <r><c>1176079329</c><c>7809329882</c></r>
 <r><c>1170216183</c><c>7805909975</c></r>
 <r><c>1166171069</c><c>7802876316</c></r>
 <r><c>1162447794</c><c>7799791459</c></r>
 <r><c>1158490241</c><c>7796612378</c></r>
 <r><c>1154136303</c><c>7794239918</c></r>
 <r><c>1149224415</c><c>7792142098</c></r>
 <r><c>1145259828</c><c>7790468654</c></r>
 <r><c>1141113934</c><c>7788437121</c></r>
 <r><c>1137043768</c><c>7786407961</c></r>
 <r><c>1132836915</c><c>7784458302</c></r>
 <r><c>1128587256</c><c>7782448683</c></r>
 <r><c>1123797011</c><c>7780248880</c></r>
 <r><c>1118841528</c><c>7777931392</c></r>
 <r><c>1112598455</c><c>7774945736</c></r>
 <r><c>1106858315</c><c>7771548707</c></r>
 <r><c>1101110827</c><c>7767792627</c></r>
 <r><c>1095570077</c><c>7764260979</c></r>
 <r><c>1089508489</c><c>7759970697</c></r>
 <r><c>1083564645</c><c>7756012216</c></r>
 <r><c>1077219341</c><c>7751261825</c></r>
 <r><c>1071206780</c><c>7747263919</c></r>
 <r><c>1065132805</c><c>7743816657</c></r>
 <r><c>1058909408</c><c>7740557052</c></r>
 <r><c>1053181630</c><c>7737749681</c></r>
 <r><c>1046849119</c><c>7734601695</c></r>
 <r><c>1040941757</c><c>7731616423</c></r>
 <r><c>1035254005</c><c>7728970927</c></r>
 <r><c>1029877984</c><c>7726292839</c></r>
 <r><c>1025091867</c><c>7724020955</c></r>
 <r><c>1019021611</c><c>7721296320</c></r>
 <r><c>1014082393</c><c>7718632907</c></r>
 <r><c>1009077554</c><c>7716449334</c></r>
 <r><c>1004057621</c><c>7714112497</c></r>
 <r><c>999381573</c><c>7712156791</c></r>
 <r><c>993978378</c><c>7709506493</c></r>
 <r><c>987868928</c><c>7706726051</c></r>
 <r><c>981641531</c><c>7703589083</c></r>
 <r><c>975188587</c><c>7700343965</c></r>
 <r><c>968529284</c><c>7696630367</c></r>
 <r><c>962046394</c><c>7693243958</c></r>
 <r><c>955161641</c><c>7689491972</c></r>
 <r><c>948028801</c><c>7685169725</c></r>
 <r><c>941201668</c><c>7681528264</c></r>
 <r><c>934319028</c><c>7677684166</c></r>
 <r><c>927238755</c><c>7673926040</c></r>
 <r><c>921248243</c><c>7671000207</c></r>
 <r><c>914874054</c><c>7667478458</c></r>
 <r><c>908945007</c><c>7662928363</c></r>
 <r><c>902529725</c><c>7658638469</c></r>
 <r><c>897610936</c><c>7654546784</c></r>
 <r><c>892649059</c><c>7650934597</c></r>
 <r><c>887591154</c><c>7647686505</c></r>
 <r><c>882285405</c><c>7644929014</c></r>
 <r><c>877645361</c><c>7642547648</c></r>
 <r><c>872204224</c><c>7639835813</c></r>
 <r><c>867429350</c><c>7637735046</c></r>
 <r><c>863271918</c><c>7636414605</c></r>
 <r><c>858095577</c><c>7634541403</c></r>
 <r><c>853393067</c><c>7633075503</c></r>
 <r><c>848007179</c><c>7631219862</c></r>
 <r><c>842462374</c><c>7629339560</c></r>
 <r><c>836918857</c><c>7627686783</c></r>
 <r><c>829762863</c><c>7625279677</c></r>
 <r><c>822967358</c><c>7622416870</c></r>
 <r><c>816067378</c><c>7619052540</c></r>
 <r><c>808687577</c><c>7615833994</c></r>
 <r><c>801619714</c><c>7612824986</c></r>
 <r><c>795041338</c><c>7608605228</c></r>
 <r><c>788059151</c><c>7605118512</c></r>
 <r><c>781531210</c><c>7602013665</c></r>
 <r><c>774891739</c><c>7598501572</c></r>
 <r><c>768254524</c><c>7594285776</c></r>
 <r><c>763226180</c><c>7589975268</c></r>
 <r><c>758008129</c><c>7584904727</c></r>
 <r><c>753357339</c><c>7580682951</c></r>
 <r><c>748272536</c><c>7576235286</c></r>
 <r><c>743586029</c><c>7572918949</c></r>
 <r><c>738851056</c><c>7569879693</c></r>
 <r><c>733870509</c><c>7567286809</c></r>
 <r><c>728134313</c><c>7564840464</c></r>
 <r><c>723225548</c><c>7562513101</c></r>
 <r><c>719175676</c><c>7560591857</c></r>
 <r><c>714641933</c><c>7558264451</c></r>
 <r><c>710053934</c><c>7555950413</c></r>
 <r><c>704264653</c><c>7553047782</c></r>
 <r><c>698432392</c><c>7549813259</c></r>
 <r><c>691954899</c><c>7546514603</c></r>
 <r><c>686057201</c><c>7543207358</c></r>
 <r><c>678796500</c><c>7538935883</c></r>
 <r><c>672517124</c><c>7534314984</c></r>
 <r><c>665090981</c><c>7529393763</c></r>
 <r><c>659140690</c><c>7524117757</c></r>
 <r><c>653379956</c><c>7519586093</c></r>
 <r><c>647967547</c><c>7515519738</c></r>
 <r><c>642964772</c><c>7512061047</c></r>
 <r><c>637491374</c><c>7508682916</c></r>
 <r><c>630808114</c><c>7505865498</c></r>
 <r><c>625330748</c><c>7502950127</c></r>
 <r><c>619952755</c><c>7500340713</c></r>
 <r><c>614597163</c><c>7497546854</c></r>
 <r><c>609591862</c><c>7495032901</c></r>
 <r><c>604013662</c><c>7492369854</c></r>
 <r><c>599111144</c><c>7490341484</c></r>
 <r><c>594291074</c><c>7488472390</c></r>
 <r><c>590140951</c><c>7486894358</c></r>
 <r><c>586197353</c><c>7485290555</c></r>
 <r><c>581954534</c><c>7483371995</c></r>
 <r><c>577947034</c><c>7481719070</c></r>
 <r><c>572025063</c><c>7479405549</c></r>
 <r><c>566472475</c><c>7477233111</c></r>
 <r><c>560636454</c><c>7474370587</c></r>
 <r><c>554345089</c><c>7472102310</c></r>
 <r><c>548297287</c><c>7469663116</c></r>
 <r><c>542129808</c><c>7465806785</c></r>
 <r><c>536169034</c><c>7461704404</c></r>
 <r><c>529681600</c><c>7458462014</c></r>
 <r><c>524316710</c><c>7456304805</c></r>
 <r><c>518436189</c><c>7453416566</c></r>
 <r><c>513267607</c><c>7450757391</c></r>
 <r><c>507498446</c><c>7446537862</c></r>
 <r><c>500860349</c><c>7442274942</c></r>
 <r><c>495279303</c><c>7438590150</c></r>
 <r><c>490621307</c><c>7434859716</c></r>
 <r><c>486559419</c><c>7431782465</c></r>
 <r><c>481559361</c><c>7427964992</c></r>
 <r><c>477254055</c><c>7424914626</c></r>
 <r><c>472240512</c><c>7421703418</c></r>
 <r><c>466489875</c><c>7419440043</c></r>
 <r><c>462231459</c><c>7417555439</c></r>
 <r><c>457929288</c><c>7415683712</c></r>
 <r><c>453605075</c><c>7413794523</c></r>
 <r><c>448517050</c><c>7411578137</c></r>
 <r><c>443548020</c><c>7409563482</c></r>
 <r><c>436958022</c><c>7406895963</c></r>
 <r><c>430542620</c><c>7404622903</c></r>
 <r><c>423558783</c><c>7402386892</c></r>
 <r><c>416127803</c><c>7399534776</c></r>
 <r><c>409858632</c><c>7396538867</c></r>
 <r><c>404126098</c><c>7392736333</c></r>
 <r><c>398450383</c><c>7388863484</c></r>
 <r><c>392541914</c><c>7384709194</c></r>
 <r><c>387292361</c><c>7381462522</c></r>
 <r><c>381636422</c><c>7378546852</c></r>
 <r><c>375824509</c><c>7375234271</c></r>
 <r><c>370717544</c><c>7371996382</c></r>
 <r><c>365502668</c><c>7369071006</c></r>
 <r><c>360355610</c><c>7366285004</c></r>
 <r><c>355152314</c><c>7363676234</c></r>
 <r><c>350453353</c><c>7359942854</c></r>
 <r><c>346158854</c><c>7356393868</c></r>
 <r><c>341440771</c><c>7353051562</c></r>
 <r><c>336981961</c><c>7350975643</c></r>
 <r><c>332484314</c><c>7348744743</c></r>
 <r><c>328665618</c><c>7347252578</c></r>
 <r><c>324180160</c><c>7345262816</c></r>
 <r><c>319655438</c><c>7343321139</c></r>
 <r><c>314002954</c><c>7340661391</c></r>
 <r><c>308328397</c><c>7338169544</c></r>
 <r><c>301652276</c><c>7335512179</c></r>
 <r><c>294224322</c><c>7332256050</c></r>
 <r><c>286861269</c><c>7329529542</c></r>
 <r><c>279465876</c><c>7326681984</c></r>
 <r><c>273832948</c><c>7323931669</c></r>
 <r><c>266945792</c><c>7321134449</c></r>
 <r><c>261776324</c><c>7318425255</c></r>
 <r><c>256819099</c><c>7315340551</c></r>
 <r><c>252198050</c><c>7312653130</c></r>
 <r><c>247484921</c><c>7309265227</c></r>
 <r><c>242990005</c><c>7306356518</c></r>
 <r><c>238177537</c><c>7303791671</c></r>
 <r><c>233053647</c><c>7301013991</c></r>
 <r><c>227701492</c><c>7298269212</c></r>
 <r><c>223060196</c><c>7295306075</c></r>
 <r><c>218885978</c><c>7291761901</c></r>
 <r><c>214850766</c><c>7288591093</c></r>
 <r><c>211047438</c><c>7285714714</c></r>
 <r><c>207312084</c><c>7282807151</c></r>
 <r><c>203185536</c><c>7279872994</c></r>
 <r><c>198181733</c><c>7276921276</c></r>
 <r><c>193475357</c><c>7273265665</c></r>
 <r><c>188631218</c><c>7269486839</c></r>
 <r><c>183240310</c><c>7265530621</c></r>
 <r><c>177356351</c><c>7262104732</c></r>
 <r><c>171325756</c><c>7258194034</c></r>
 <r><c>165200059</c><c>7254846098</c></r>
 <r><c>158777999</c><c>7251002511</c></r>
 <r><c>151518139</c><c>7247353315</c></r>
 <r><c>143836451</c><c>7243294077</c></r>
 <r><c>136679724</c><c>7240521608</c></r>
 <r><c>130624578</c><c>7238080210</c></r>
 <r><c>125303846</c><c>7235729707</c></r>
 <r><c>119361494</c><c>7232430247</c></r>
 <r><c>114374667</c><c>7228890721</c></r>
 <r><c>109132519</c><c>7225447407</c></r>
 <r><c>105026948</c><c>7222635672</c></r>
 <r><c>99905522</c><c>7219059279</c></r>
 <r><c>94854543</c><c>7216541059</c></r>
 <r><c>90125823</c><c>7214009391</c></r>
 <r><c>86054859</c><c>7212191700</c></r>
 <r><c>81537549</c><c>7209677932</c></r>
 <r><c>77456577</c><c>7207754805</c></r>
 <r><c>72056887</c><c>7205382880</c></r>
 <r><c>67001765</c><c>7203584790</c></r>
 <r><c>60523143</c><c>7201069131</c></r>
 <r><c>54847407</c><c>7199268833</c></r>
 <r><c>48640746</c><c>7197036544</c></r>
 <r><c>41920925</c><c>7194907249</c></r>
 <r><c>35258372</c><c>7192834683</c></r>
 <r><c>28871623</c><c>7190104638</c></r>
 <r><c>22136308</c><c>7186763924</c></r>
 <r><c>15066802</c><c>7183436804</c></r>
 <r><c>8253818</c><c>7179871420</c></r>
 <r><c>1929541</c><c>7177140699</c></r>
 <r><c>-4467753</c><c>7174519667</c></r>
 <r><c>-10153366</c><c>7172016500</c></r>
 <r><c>-16012111</c><c>7168804286</c></r>
 <r><c>-21630729</c><c>7165547760</c></r>
 <r><c>-27003865</c><c>7162305482</c></r>
 <r><c>-31431851</c><c>7159322321</c></r>
 <r><c>-37063344</c><c>7156388368</c></r>
 <r><c>-41738453</c><c>7153743764</c></r>
 <r><c>-46581206</c><c>7150913315</c></r>
 <r><c>-51097671</c><c>7148858104</c></r>
 <r><c>-56529640</c><c>7146684793</c></r>
 <r><c>-60624170</c><c>7144466897</c></r>
 <r><c>-64987750</c><c>7142229847</c></r>
 <r><c>-69073157</c><c>7139904515</c></r>
 <r><c>-73795903</c><c>7137582128</c></r>
 <r><c>-78414353</c><c>7135559295</c></r>
 <r><c>-83529071</c><c>7133179161</c></r>
 <r><c>-89142743</c><c>7130772856</c></r>
 <r><c>-94830095</c><c>7128086581</c></r>
 <r><c>-100842745</c><c>7125654524</c></r>
 <r><c>-107280001</c><c>7122205343</c></r>
 <r><c>-114064449</c><c>7118290847</c></r>
 <r><c>-118921635</c><c>7115021816</c></r>
 <r><c>-125049156</c><c>7112223755</c></r>
 <r><c>-130261283</c><c>7109756838</c></r>
 <r><c>-136769113</c><c>7106630216</c></r>
 <r><c>-142882971</c><c>7103208027</c></r>
 <r><c>-148206349</c><c>7099593582</c></r>
 <r><c>-152968291</c><c>7096112325</c></r>
 <r><c>-158485402</c><c>7092922534</c></r>
 <r><c>-163458701</c><c>7090204269</c></r>
 <r><c>-168003231</c><c>7087138706</c></r>
 <r><c>-171909902</c><c>7083833479</c></r>
 <r><c>-176620113</c><c>7081073183</c></r>
 <r><c>-181846566</c><c>7079323334</c></r>
 <r><c>-186127637</c><c>7077342415</c></r>
 <r><c>-189694634</c><c>7075699284</c></r>
 <r><c>-194119737</c><c>7073442688</c></r>
 <r><c>-198121485</c><c>7071011919</c></r>
 <r><c>-202983971</c><c>7068323250</c></r>
 <r><c>-208036373</c><c>7065763359</c></r>
 <r><c>-213571891</c><c>7062484745</c></r>
 <r><c>-219650802</c><c>7059504213</c></r>
 <r><c>-226432737</c><c>7056015306</c></r>
 <r><c>-233598771</c><c>7052537105</c></r>
 <r><c>-239800419</c><c>7049226996</c></r>
 <r><c>-245547044</c><c>7045894145</c></r>
 <r><c>-250708367</c><c>7042358937</c></r>
 <r><c>-255668961</c><c>7039120446</c></r>
 <r><c>-260325083</c><c>7036169136</c></r>
 <r><c>-265121901</c><c>7033262721</c></r>
 <r><c>-270910549</c><c>7030527329</c></r>
 <r><c>-275242587</c><c>7027659982</c></r>
 <r><c>-280993442</c><c>7024356711</c></r>
 <r><c>-285881398</c><c>7021433476</c></r>
 <r><c>-290343949</c><c>7018170522</c></r>
 <r><c>-295834041</c><c>7015097350</c></r>
 <r><c>-300354758</c><c>7012514502</c></r>
 <r><c>-305743831</c><c>7010052380</c></r>
 <r><c>-309766711</c><c>7008214092</c></r>
 <r><c>-313525059</c><c>7006132018</c></r>
 <r><c>-317186684</c><c>7004728284</c></r>
 <r><c>-321753607</c><c>7002772695</c></r>
 <r><c>-326046120</c><c>7000807138</c></r>
 <r><c>-331072239</c><c>6998451533</c></r>
 <r><c>-336292538</c><c>6996529933</c></r>
 <r><c>-343003335</c><c>6993324421</c></r>
 <r><c>-349366721</c><c>6989172911</c></r>
 <r><c>-356445079</c><c>6984367728</c></r>
 <r><c>-362679757</c><c>6979502221</c></r>
 <r><c>-368698079</c><c>6974786371</c></r>
 <r><c>-374269535</c><c>6970981598</c></r>
 <r><c>-379811732</c><c>6967292638</c></r>
 <r><c>-384494007</c><c>6962964455</c></r>
 <r><c>-389495540</c><c>6958454197</c></r>
 <r><c>-394130749</c><c>6954088497</c></r>
 <r><c>-399127590</c><c>6950382721</c></r>
 <r><c>-403862070</c><c>6947027449</c></r>
 <r><c>-408717153</c><c>6944299870</c></r>
 <r><c>-413384339</c><c>6941477024</c></r>
 <r><c>-418593335</c><c>6938850951</c></r>
 <r><c>-422671028</c><c>6936504813</c></r>
 <r><c>-428674448</c><c>6933254533</c></r>
 <r><c>-432564368</c><c>6931662038</c></r>
 <r><c>-436525033</c><c>6929725862</c></r>
 <r><c>-440222559</c><c>6928048284</c></r>
 <r><c>-444318362</c><c>6926029440</c></r>
 <r><c>-448638334</c><c>6924196384</c></r>
 <r><c>-454061100</c><c>6921767944</c></r>
 <r><c>-458846550</c><c>6919374926</c></r>
 <r><c>-464450759</c><c>6916527173</c></r>
 <r><c>-470219135</c><c>6913613703</c></r>
 <r><c>-476537555</c><c>6911071881</c></r>
 <r><c>-482614973</c><c>6908341236</c></r>
 <r><c>-488532026</c><c>6905392147</c></r>
 <r><c>-494185620</c><c>6902773071</c></r>
 <r><c>-499717981</c><c>6900205521</c></r>
 <r><c>-504694010</c><c>6898363605</c></r>
 <r><c>-510564136</c><c>6895771910</c></r>
 <r><c>-516674639</c><c>6892925748</c></r>
 <r><c>-522787370</c><c>6890269986</c></r>
 <r><c>-527231955</c><c>6888142634</c></r>
 <r><c>-532209504</c><c>6885609535</c></r>
 <r><c>-537264264</c><c>6882728870</c></r>
 <r><c>-542672463</c><c>6879641847</c></r>
 <r><c>-547480416</c><c>6876913993</c></r>
 <r><c>-551868252</c><c>6874759806</c></r>
 <r><c>-555743086</c><c>6872305844</c></r>
 <r><c>-559487572</c><c>6870291983</c></r>
 <r><c>-563464462</c><c>6868214756</c></r>
 <r><c>-567560007</c><c>6866276157</c></r>
 <r><c>-571975219</c><c>6863811366</c></r>
 <r><c>-577073781</c><c>6861583494</c></r>
 <r><c>-582926942</c><c>6859063362</c></r>
 <r><c>-589033609</c><c>6856394623</c></r>
 <r><c>-596176851</c><c>6852224159</c></r>
 <r><c>-602150793</c><c>6848456839</c></r>
 <r><c>-607648901</c><c>6844275057</c></r>
 <r><c>-613085680</c><c>6841046681</c></r>
 <r><c>-619219343</c><c>6836738433</c></r>
 <r><c>-624934242</c><c>6833105777</c></r>
 <r><c>-630307853</c><c>6829281726</c></r>
 <r><c>-635616448</c><c>6826027582</c></r>
 <r><c>-640528428</c><c>6822854579</c></r>
 <r><c>-645825479</c><c>6819988083</c></r>
 <r><c>-652954513</c><c>6816848014</c></r>
 <r><c>-659560242</c><c>6814021644</c></r>
 <r><c>-664144883</c><c>6811362207</c></r>
 <r><c>-668448404</c><c>6808778055</c></r>
 <r><c>-672601834</c><c>6806580441</c></r>
 <r><c>-676671956</c><c>6803839496</c></r>
 <r><c>-680388893</c><c>6801425326</c></r>
 <r><c>-684504647</c><c>6798521824</c></r>
 <r><c>-688745321</c><c>6795940111</c></r>
 <r><c>-693917505</c><c>6792987420</c></r>
 <r><c>-698575525</c><c>6790271095</c></r>
 <r><c>-704717947</c><c>6786659690</c></r>
 <r><c>-711358589</c><c>6783142410</c></r>
 <r><c>-717728547</c><c>6779438656</c></r>
 <r><c>-724427587</c><c>6776046958</c></r>
 <r><c>-731256542</c><c>6772026087</c></r>
 <r><c>-736719423</c><c>6767606572</c></r>
 <r><c>-741529802</c><c>6763501054</c></r>
 <r><c>-746721911</c><c>6759255184</c></r>
 <r><c>-751913217</c><c>6755233406</c></r>
 <r><c>-756949235</c><c>6751260871</c></r>
 <r><c>-761707471</c><c>6747910155</c></r>
 <r><c>-767411225</c><c>6744272604</c></r>
 <r><c>-772034489</c><c>6741123598</c></r>
 <r><c>-776918086</c><c>6737878209</c></r>
 <r><c>-780964502</c><c>6735087807</c></r>
 <r><c>-786004257</c><c>6731910756</c></r>
 <r><c>-789434791</c><c>6729739582</c></r>
 <r><c>-793334737</c><c>6727380130</c></r>
 <r><c>-796941814</c><c>6725138701</c></r>
 <r><c>-800596920</c><c>6722570823</c></r>
 <r><c>-804891890</c><c>6720116940</c></r>
 <r><c>-809443547</c><c>6717445741</c></r>
 <r><c>-814114850</c><c>6714424982</c></r>
 <r><c>-819045142</c><c>6711578121</c></r>
 <r><c>-824143815</c><c>6708908806</c></r>
 <r><c>-829483505</c><c>6705726223</c></r>
 <r><c>-835389959</c><c>6702865002</c></r>
 <r><c>-841034395</c><c>6700720845</c></r>
 <r><c>-846904762</c><c>6696958353</c></r>
 <r><c>-852302205</c><c>6693243541</c></r>
 <r><c>-858719196</c><c>6688981539</c></r>
 <r><c>-863612766</c><c>6685111754</c></r>
 <r><c>-868890023</c><c>6681870731</c></r>
 <r><c>-874748458</c><c>6678468230</c></r>
 <r><c>-881478473</c><c>6674915893</c></r>
 <r><c>-886928859</c><c>6671974470</c></r>
 <r><c>-892873602</c><c>6668876933</c></r>
 <r><c>-897369805</c><c>6665821456</c></r>
 <r><c>-902262425</c><c>6662675810</c></r>
 <r><c>-906476270</c><c>6659575953</c></r>
 <r><c>-910475062</c><c>6656772893</c></r>
 <r><c>-913588879</c><c>6654189387</c></r>
 <r><c>-917710184</c><c>6652253512</c></r>
 <r><c>-921134532</c><c>6649805318</c></r>
 <r><c>-923749160</c><c>6648014240</c></r>
 <r><c>-926799950</c><c>6645983308</c></r>
 <r><c>-929608664</c><c>6643905818</c></r>
 <r><c>-933671679</c><c>6641779243</c></r>
 <r><c>-937782520</c><c>6639203222</c></r>
 <r><c>-943101564</c><c>6635782200</c></r>
 <r><c>-948522057</c><c>6632802264</c></r>
 <r><c>-954074080</c><c>6629932123</c></r>
 <r><c>-960301689</c><c>6626819212</c></r>
 <r><c>-966564889</c><c>6622491704</c></r>
 <r><c>-972721024</c><c>6618684357</c></r>
 <r><c>-979291219</c><c>6614603527</c></r>
 <r><c>-984803805</c><c>6611240074</c></r>
 <r><c>-991437915</c><c>6607354047</c></r>
 <r><c>-997272698</c><c>6603772976</c></r>
 <r><c>-1003039240</c><c>6599686501</c></r>
 <r><c>-1007287808</c><c>6595739634</c></r>
 <r><c>-1011631620</c><c>6591534590</c></r>
 <r><c>-1015993074</c><c>6588574223</c></r>
 <r><c>-1020194664</c><c>6585278644</c></r>
 <r><c>-1023842987</c><c>6581785712</c></r>
 <r><c>-1027061644</c><c>6578023549</c></r>
 <r><c>-1029705248</c><c>6575696538</c></r>
 <r><c>-1032652820</c><c>6573188422</c></r>
 <r><c>-1035051252</c><c>6571280334</c></r>
 <r><c>-1038849787</c><c>6569002662</c></r>
 <r><c>-1042329780</c><c>6566618004</c></r>
 <r><c>-1045870355</c><c>6563641281</c></r>
 <r><c>-1049248218</c><c>6560790131</c></r>
 <r><c>-1053201348</c><c>6557990636</c></r>
 <r><c>-1058771833</c><c>6554534835</c></r>
 <r><c>-1064463107</c><c>6550924940</c></r>
 <r><c>-1070424322</c><c>6546943248</c></r>
 <r><c>-1075175214</c><c>6543502586</c></r>
 <r><c>-1079579287</c><c>6539821088</c></r>
 <r><c>-1083540485</c><c>6536162157</c></r>
 <r><c>-1088171480</c><c>6532343598</c></r>
 <r><c>-1091833365</c><c>6529113738</c></r>
 <r><c>-1095845716</c><c>6525654508</c></r>
 <r><c>-1100303124</c><c>6521613210</c></r>
 <r><c>-1104813241</c><c>6517422753</c></r>
 <r><c>-1108774885</c><c>6514441645</c></r>
 <r><c>-1112803574</c><c>6511427005</c></r>
 <r><c>-1116468715</c><c>6508519722</c></r>
 <r><c>-1119369543</c><c>6505673395</c></r>
 <r><c>-1123113539</c><c>6502923734</c></r>
 <r><c>-1126167411</c><c>6501087465</c></r>
 <r><c>-1129393824</c><c>6498128552</c></r>
 <r><c>-1132260595</c><c>6495977986</c></r>
 <r><c>-1135235743</c><c>6493377233</c></r>
 <r><c>-1138061032</c><c>6490911329</c></r>
 <r><c>-1141487217</c><c>6488401652</c></r>
 <r><c>-1145286689</c><c>6485374246</c></r>
 <r><c>-1149544891</c><c>6482499823</c></r>
 <r><c>-1154743450</c><c>6479377818</c></r>
 <r><c>-1160276717</c><c>6474654440</c></r>
 <r><c>-1166332536</c><c>6470033520</c></r>
 <r><c>-1172650582</c><c>6465663743</c></r>
 <r><c>-1177208833</c><c>6460844509</c></r>
 <r><c>-1181483032</c><c>6456695412</c></r>
 <r><c>-1185847067</c><c>6452198101</c></r>
 <r><c>-1191777116</c><c>6448228468</c></r>
 <r><c>-1196512963</c><c>6443979837</c></r>
 <r><c>-1200186058</c><c>6440494865</c></r>
 <r><c>-1203047101</c><c>6437147738</c></r>
 <r><c>-1205916009</c><c>6433647290</c></r>
 <r><c>-1208742077</c><c>6430300320</c></r>
 <r><c>-1211785138</c><c>6426768347</c></r>
 <r><c>-1214809606</c><c>6423326153</c></r>
 <r><c>-1217860981</c><c>6420607943</c></r>
 <r><c>-1221228234</c><c>6417462234</c></r>
 <r><c>-1223476644</c><c>6414597926</c></r>
 <r><c>-1225756814</c><c>6411445270</c></r>
 <r><c>-1228502301</c><c>6408117855</c></r>
 <r><c>-1230940505</c><c>6405282572</c></r>
 <r><c>-1233827945</c><c>6401889022</c></r>
 <r><c>-1236553596</c><c>6398516276</c></r>
 <r><c>-1242270724</c><c>6394975190</c></r>
 <r><c>-1245748255</c><c>6391538601</c></r>
 <r><c>-1249867035</c><c>6387857022</c></r>
 <r><c>-1254395449</c><c>6382945683</c></r>
 <r><c>-1258779131</c><c>6378052678</c></r>
 <r><c>-1263585347</c><c>6373330345</c></r>
 <r><c>-1268455924</c><c>6368423985</c></r>
 <r><c>-1272837430</c><c>6364983237</c></r>
 <r><c>-1278045141</c><c>6361128111</c></r>
 <r><c>-1281630265</c><c>6357357899</c></r>
 <r><c>-1284838258</c><c>6353648947</c></r>
 <r><c>-1288142919</c><c>6349561927</c></r>
 <r><c>-1291552463</c><c>6345164527</c></r>
 <r><c>-1295409417</c><c>6341909906</c></r>
 <r><c>-1298633898</c><c>6338679168</c></r>
 <r><c>-1301661994</c><c>6335587714</c></r>
 <r><c>-1305333071</c><c>6333251375</c></r>
 <r><c>-1308264353</c><c>6331646333</c></r>
 <r><c>-1310392797</c><c>6329913210</c></r>
 <r><c>-1313000856</c><c>6327758042</c></r>
 <r><c>-1315334828</c><c>6325841422</c></r>
 <r><c>-1317769875</c><c>6323788882</c></r>
 <r><c>-1320956122</c><c>6321197031</c></r>
 <r><c>-1324172455</c><c>6318288865</c></r>
 <r><c>-1328269604</c><c>6315089769</c></r>
 <r><c>-1333621548</c><c>6311225046</c></r>
 <r><c>-1338938554</c><c>6307100308</c></r>
 <r><c>-1344499215</c><c>6302248148</c></r>
 <r><c>-1349220458</c><c>6297813924</c></r>
 <r><c>-1353625865</c><c>6293838533</c></r>
 <r><c>-1358078091</c><c>6289843592</c></r>
 <r><c>-1362180814</c><c>6287855185</c></r>
 <r><c>-1367125503</c><c>6285567532</c></r>
 <r><c>-1370776089</c><c>6283639617</c></r>
 <r><c>-1374141318</c><c>6282308312</c></r>
 <r><c>-1377581213</c><c>6280131739</c></r>
 <r><c>-1380652029</c><c>6277219126</c></r>
 <r><c>-1383645765</c><c>6274757104</c></r>
 <r><c>-1386971901</c><c>6271859347</c></r>
 <r><c>-1389862302</c><c>6268609754</c></r>
 <r><c>-1393047459</c><c>6264900997</c></r>
 <r><c>-1395613283</c><c>6261566608</c></r>
 <r><c>-1398046865</c><c>6258161954</c></r>
 <r><c>-1401145915</c><c>6254447093</c></r>
 <r><c>-1404269814</c><c>6251224613</c></r>
 <r><c>-1409075212</c><c>6248498400</c></r>
 <r><c>-1413998202</c><c>6245975808</c></r>
 <r><c>-1419763580</c><c>6242346730</c></r>
 <r><c>-1425951738</c><c>6237324536</c></r>
 <r><c>-1432450791</c><c>6232865542</c></r>
 <r><c>-1439584820</c><c>6228010564</c></r>
 <r><c>-1445282032</c><c>6223401450</c></r>
 <r><c>-1450799641</c><c>6218634535</c></r>
 <r><c>-1456448957</c><c>6213212604</c></r>
 <r><c>-1462609578</c><c>6208849650</c></r>
 <r><c>-1468814817</c><c>6205081372</c></r>
 <r><c>-1474608234</c><c>6201646741</c></r>
 <r><c>-1480285198</c><c>6197854903</c></r>
 <r><c>-1484987613</c><c>6193755110</c></r>
 <r><c>-1489231666</c><c>6189582242</c></r>
 <r><c>-1493728565</c><c>6185492327</c></r>
 <r><c>-1497876560</c><c>6181678760</c></r>
 <r><c>-1501750503</c><c>6178043862</c></r>
 <r><c>-1505208307</c><c>6174810099</c></r>
 <r><c>-1508729056</c><c>6171255904</c></r>
 <r><c>-1511799511</c><c>6168207027</c></r>
 <r><c>-1515096034</c><c>6165137207</c></r>
 <r><c>-1518711718</c><c>6161828939</c></r>
 <r><c>-1521942970</c><c>6158741064</c></r>
 <r><c>-1526561062</c><c>6155333955</c></r>
 <r><c>-1530905846</c><c>6152029318</c></r>
 <r><c>-1536151655</c><c>6148776535</c></r>
 <r><c>-1541963850</c><c>6145557253</c></r>
 <r><c>-1547383484</c><c>6143285220</c></r>
 <r><c>-1552667026</c><c>6140497739</c></r>
 <r><c>-1558024325</c><c>6137522693</c></r>
 <r><c>-1563779369</c><c>6134258760</c></r>
 <r><c>-1569615202</c><c>6130806152</c></r>
 <r><c>-1574165519</c><c>6127404455</c></r>
 <r><c>-1578523812</c><c>6123894499</c></r>
 <r><c>-1583349743</c><c>6120191115</c></r>
 <r><c>-1588264361</c><c>6116863369</c></r>
 <r><c>-1593165889</c><c>6113787402</c></r>
 <r><c>-1598142023</c><c>6109186002</c></r>
 <r><c>-1601969594</c><c>6104589093</c></r>
 <r><c>-1606362257</c><c>6100533752</c></r>
 <r><c>-1610431690</c><c>6096917727</c></r>
 <r><c>-1614335738</c><c>6093283285</c></r>
 <r><c>-1618497736</c><c>6088918880</c></r>
 <r><c>-1622648438</c><c>6085399404</c></r>
 <r><c>-1626426650</c><c>6081571490</c></r>
 <r><c>-1630234921</c><c>6078221659</c></r>
 <r><c>-1633802262</c><c>6075114096</c></r>
 <r><c>-1638113996</c><c>6071233024</c></r>
 <r><c>-1642725961</c><c>6068093627</c></r>
 <r><c>-1647818806</c><c>6064653938</c></r>
 <r><c>-1654137192</c><c>6061162750</c></r>
 <r><c>-1660450515</c><c>6057180730</c></r>
 <r><c>-1667832283</c><c>6053113995</c></r>
 <r><c>-1674956099</c><c>6049915454</c></r>
 <r><c>-1681573646</c><c>6046355924</c></r>
 <r><c>-1687003022</c><c>6043519369</c></r>
 <r><c>-1691815488</c><c>6040378359</c></r>
 <r><c>-1696854623</c><c>6037238028</c></r>
 <r><c>-1701690488</c><c>6033470108</c></r>
 <r><c>-1706662790</c><c>6029046507</c></r>
 <r><c>-1711560371</c><c>6024284546</c></r>
 <r><c>-1716140076</c><c>6020636000</c></r>
 <r><c>-1720524820</c><c>6017843109</c></r>
 <r><c>-1724907063</c><c>6013805773</c></r>
 <r><c>-1729074963</c><c>6010223981</c></r>
 <r><c>-1733622099</c><c>6006740843</c></r>
 <r><c>-1737502707</c><c>6004081109</c></r>
 <r><c>-1741892072</c><c>6001605889</c></r>
 <r><c>-1745313975</c><c>5999393407</c></r>
 <r><c>-1748710395</c><c>5997241493</c></r>
 <r><c>-1752138274</c><c>5995041418</c></r>
 <r><c>-1756002398</c><c>5992357706</c></r>
 <r><c>-1760291212</c><c>5990005011</c></r>
 <r><c>-1764389142</c><c>5987359508</c></r>
 <r><c>-1768993735</c><c>5984690368</c></r>
 <r><c>-1774638880</c><c>5981372829</c></r>
 <r><c>-1780539160</c><c>5976422796</c></r>
 <r><c>-1785917915</c><c>5971259262</c></r>
 <r><c>-1790607279</c><c>5966127980</c></r>
 <r><c>-1796187653</c><c>5961819926</c></r>
 <r><c>-1801397174</c><c>5957319192</c></r>
 <r><c>-1806327728</c><c>5954914860</c></r>
 <r><c>-1812204488</c><c>5952577022</c></r>
 <r><c>-1817621948</c><c>5949579706</c></r>
 <r><c>-1822495549</c><c>5945997357</c></r>
 <r><c>-1827824048</c><c>5942563882</c></r>
 <r><c>-1832665451</c><c>5939435426</c></r>
 <r><c>-1837103147</c><c>5935769166</c></r>
 <r><c>-1841515449</c><c>5932245318</c></r>
 <r><c>-1844975266</c><c>5929589977</c></r>
 <r><c>-1848694145</c><c>5926982347</c></r>
 <r><c>-1853170425</c><c>5924615655</c></r>
 <r><c>-1856459902</c><c>5922508928</c></r>
 <r><c>-1859989466</c><c>5919771067</c></r>
 <r><c>-1863309585</c><c>5917216632</c></r>
 <r><c>-1866633112</c><c>5914976904</c></r>
 <r><c>-1870098907</c><c>5912230021</c></r>
 <r><c>-1874553372</c><c>5909466676</c></r>
 <r><c>-1879957608</c><c>5906544974</c></r>
 <r><c>-1887614443</c><c>5902595261</c></r>
 <r><c>-1893753051</c><c>5898839467</c></r>
 <r><c>-1899253054</c><c>5894085781</c></r>
 <r><c>-1905164121</c><c>5889609465</c></r>
 <r><c>-1910271115</c><c>5885802462</c></r>
 <r><c>-1915982519</c><c>5882172261</c></r>
 <r><c>-1921582197</c><c>5878694922</c></r>
 <r><c>-1926974020</c><c>5874844710</c></r>
 <r><c>-1932062232</c><c>5871685912</c></r>
 <r><c>-1937392655</c><c>5868137815</c></r>
 <r><c>-1942226217</c><c>5864817246</c></r>
 <r><c>-1946534206</c><c>5863096424</c></r>
 <r><c>-1950821350</c><c>5860798348</c></r>
 <r><c>-1954990296</c><c>5858134865</c></r>
 <r><c>-1959792299</c><c>5855349590</c></r>
 <r><c>-1964372045</c><c>5853512658</c></r>
 <r><c>-1968522287</c><c>5851836841</c></r>
 <r><c>-1972111020</c><c>5850219334</c></r>
 <r><c>-1976071083</c><c>5848159385</c></r>
 <r><c>-1980021047</c><c>5846188988</c></r>
 <r><c>-1983800647</c><c>5844570285</c></r>
 <r><c>-1988444253</c><c>5842494085</c></r>
 <r><c>-1993507833</c><c>5840398975</c></r>
 <r><c>-1998881270</c><c>5837871464</c></r>
 <r><c>-2006330608</c><c>5834617780</c></r>
 <r><c>-2014226006</c><c>5831553001</c></r>
 <r><c>-2020711974</c><c>5827865948</c></r>
 <r><c>-2026337565</c><c>5823703262</c></r>
 <r><c>-2031698599</c><c>5819394165</c></r>
 <r><c>-2038030885</c><c>5816388554</c></r>
 <r><c>-2043358536</c><c>5814044707</c></r>
 <r><c>-2048504825</c><c>5811107221</c></r>
 <r><c>-2054082349</c><c>5808418983</c></r>
 <r><c>-2059415942</c><c>5805315292</c></r>
 <r><c>-2064930163</c><c>5801335698</c></r>
 <r><c>-2069070595</c><c>5799367537</c></r>
 <r><c>-2074082065</c><c>5796772473</c></r>
 <r><c>-2079451962</c><c>5793238127</c></r>
 <r><c>-2083216186</c><c>5790409736</c></r>
 <r><c>-2087683987</c><c>5787375613</c></r>
 <r><c>-2092638676</c><c>5785146295</c></r>
 <r><c>-2096573986</c><c>5782589916</c></r>
 <r><c>-2100462265</c><c>5779833944</c></r>
 <r><c>-2104249757</c><c>5777185110</c></r>
 <r><c>-2108168838</c><c>5774479354</c></r>
 <r><c>-2112729083</c><c>5771502925</c></r>
 <r><c>-2117691784</c><c>5768865859</c></r>
 <r><c>-2122738606</c><c>5765594824</c></r>
 <r><c>-2128712368</c><c>5761994418</c></r>
 <r><c>-2135408439</c><c>5757953003</c></r>
 <r><c>-2142358530</c><c>5753041730</c></r>
 <r><c>-2149401702</c><c>5748520897</c></r>
 <r><c>-2155740367</c><c>5744991182</c></r>
 <r><c>-2161815657</c><c>5741008803</c></r>
 <r><c>-2166984944</c><c>5737045511</c></r>
 <r><c>-2171204004</c><c>5733944117</c></r>
 <r><c>-2175202507</c><c>5730825951</c></r>
 <r><c>-2179142295</c><c>5727713611</c></r>
 <r><c>-2182475526</c><c>5724839107</c></r>
 <r><c>-2186020841</c><c>5721945996</c></r>
 <r><c>-2189682125</c><c>5719165886</c></r>
 <r><c>-2192943990</c><c>5717191065</c></r>
 <r><c>-2196321004</c><c>5714768423</c></r>
 <r><c>-2199475512</c><c>5712730888</c></r>
 <r><c>-2202560618</c><c>5710739916</c></r>
 <r><c>-2205723188</c><c>5708470186</c></r>
 <r><c>-2209125723</c><c>5705882080</c></r>
 <r><c>-2212816251</c><c>5703448966</c></r>
 <r><c>-2216532957</c><c>5700900128</c></r>
 <r><c>-2220982019</c><c>5698399550</c></r>
 <r><c>-2225464018</c><c>5695735134</c></r>
 <r><c>-2229474833</c><c>5692863719</c></r>
 <r><c>-2233563001</c><c>5689253898</c></r>
 <r><c>-2237465382</c><c>5685209525</c></r>
 <r><c>-2241982182</c><c>5680568657</c></r>
 <r><c>-2246790375</c><c>5676188858</c></r>
 <r><c>-2251643020</c><c>5671849859</c></r>
 <r><c>-2257981317</c><c>5666655104</c></r>
 <r><c>-2261950335</c><c>5663388641</c></r>
 <r><c>-2265949411</c><c>5659514420</c></r>
 <r><c>-2271153127</c><c>5655561892</c></r>
 <r><c>-2275989903</c><c>5652657548</c></r>
 <r><c>-2280654685</c><c>5649670544</c></r>
 <r><c>-2284791941</c><c>5646215026</c></r>
 <r><c>-2288709739</c><c>5642842421</c></r>
 <r><c>-2292356926</c><c>5639192088</c></r>
 <r><c>-2296026949</c><c>5635856509</c></r>
 <r><c>-2299252344</c><c>5632581817</c></r>
 <r><c>-2303410391</c><c>5629605320</c></r>
 <r><c>-2307131192</c><c>5626383653</c></r>
 <r><c>-2310265933</c><c>5623565399</c></r>
 <r><c>-2313591212</c><c>5620454405</c></r>
 <r><c>-2317140952</c><c>5617363766</c></r>
 <r><c>-2321178838</c><c>5614244402</c></r>
 <r><c>-2325549738</c><c>5610812504</c></r>
 <r><c>-2330318098</c><c>5607681798</c></r>
 <r><c>-2335125142</c><c>5605287158</c></r>
 <r><c>-2339970388</c><c>5602187693</c></r>
 <r><c>-2344941249</c><c>5597729359</c></r>
 <r><c>-2350042029</c><c>5594256448</c></r>
 <r><c>-2354817827</c><c>5591197679</c></r>
 <r><c>-2360521465</c><c>5587401749</c></r>
 <r><c>-2366311084</c><c>5583148589</c></r>
 <r><c>-2371307236</c><c>5579428861</c></r>
 <r><c>-2376375856</c><c>5576210505</c></r>
 <r><c>-2380550340</c><c>5572956093</c></r>
 <r><c>-2384848251</c><c>5568857031</c></r>
 <r><c>-2389586382</c><c>5565317548</c></r>
 <r><c>-2393218461</c><c>5563047631</c></r>
 <r><c>-2396817268</c><c>5559744464</c></r>
 <r><c>-2399952734</c><c>5556071902</c></r>
 <r><c>-2402949376</c><c>5553302267</c></r>
 <r><c>-2408206029</c><c>5551229083</c></r>
 <r><c>-2412257889</c><c>5549205225</c></r>
 <r><c>-2416223156</c><c>5547078406</c></r>
 <r><c>-2420334642</c><c>5545334127</c></r>
 <r><c>-2424421853</c><c>5543477046</c></r>
 <r><c>-2428282958</c><c>5541704170</c></r>
 <r><c>-2432689204</c><c>5539720232</c></r>
 <r><c>-2437705972</c><c>5537298825</c></r>
 <r><c>-2443232206</c><c>5534283768</c></r>
 <r><c>-2449372173</c><c>5530615010</c></r>
 <r><c>-2455136388</c><c>5527984609</c></r>
 <r><c>-2460973561</c><c>5524699120</c></r>
 <r><c>-2467301989</c><c>5521399833</c></r>
 <r><c>-2472980153</c><c>5518620183</c></r>
 <r><c>-2478387484</c><c>5515479590</c></r>
 <r><c>-2483146312</c><c>5512442874</c></r>
 <r><c>-2488558381</c><c>5509291447</c></r>
 <r><c>-2494227771</c><c>5506119443</c></r>
 <r><c>-2499384040</c><c>5502786908</c></r>
 <r><c>-2504201047</c><c>5499724528</c></r>
 <r><c>-2509073106</c><c>5496542390</c></r>
 <r><c>-2513352576</c><c>5492256109</c></r>
 <r><c>-2517479731</c><c>5488508020</c></r>
 <r><c>-2521448853</c><c>5485111597</c></r>
 <r><c>-2526068943</c><c>5482212432</c></r>
 <r><c>-2529388266</c><c>5478902773</c></r>
 <r><c>-2532829679</c><c>5475841999</c></r>
 <r><c>-2536117899</c><c>5472843162</c></r>
 <r><c>-2539347720</c><c>5469955209</c></r>
 <r><c>-2543244058</c><c>5466874547</c></r>
 <r><c>-2548240231</c><c>5463534166</c></r>
 <r><c>-2553383187</c><c>5459943567</c></r>
 <r><c>-2558984269</c><c>5454805074</c></r>
 <r><c>-2565172474</c><c>5449314757</c></r>
 <r><c>-2571782115</c><c>5444815614</c></r>
 <r><c>-2578358624</c><c>5440030651</c></r>
 <r><c>-2584580308</c><c>5436424466</c></r>
 <r><c>-2591104468</c><c>5433082676</c></r>
 <r><c>-2596988216</c><c>5429048075</c></r>
 <r><c>-2602720770</c><c>5425399482</c></r>
 <r><c>-2607712979</c><c>5423294506</c></r>
 <r><c>-2613347606</c><c>5420650248</c></r>
 <r><c>-2618928368</c><c>5417531670</c></r>
 <r><c>-2622438153</c><c>5414807044</c></r>
 <r><c>-2626426272</c><c>5412441038</c></r>
 <r><c>-2629766562</c><c>5408533067</c></r>
 <r><c>-2632951557</c><c>5404972211</c></r>
 <r><c>-2635938897</c><c>5401536991</c></r>
 <r><c>-2638628573</c><c>5399474711</c></r>
 <r><c>-2641452082</c><c>5396390758</c></r>
 <r><c>-2643389707</c><c>5394019482</c></r>
 <r><c>-2645524894</c><c>5392422543</c></r>
 <r><c>-2647961931</c><c>5390661129</c></r>
 <r><c>-2651027984</c><c>5388667597</c></r>
 <r><c>-2654474127</c><c>5386652330</c></r>
 <r><c>-2658005240</c><c>5382706685</c></r>
 <r><c>-2662639980</c><c>5378422821</c></r>
 <r><c>-2668193099</c><c>5375251964</c></r>
 <r><c>-2673188574</c><c>5372776672</c></r>
 <r><c>-2678740397</c><c>5369516969</c></r>
 <r><c>-2683798500</c><c>5366484607</c></r>
 <r><c>-2688143436</c><c>5363910031</c></r>
 <r><c>-2692468908</c><c>5360530507</c></r>
 <r><c>-2697671734</c><c>5357425780</c></r>
 <r><c>-2701585680</c><c>5355146337</c></r>
 <r><c>-2704604560</c><c>5352474389</c></r>
 <r><c>-2707469996</c><c>5349392390</c></r>
 <r><c>-2710802172</c><c>5346322455</c></r>
 <r><c>-2713871804</c><c>5342634319</c></r>
 <r><c>-2717743893</c><c>5337757818</c></r>
 <r><c>-2721894729</c><c>5333414755</c></r>
 <r><c>-2725268636</c><c>5330410956</c></r>
 <r><c>-2729190655</c><c>5327593773</c></r>
 <r><c>-2732342169</c><c>5324903295</c></r>
 <r><c>-2735288408</c><c>5322586739</c></r>
 <r><c>-2738172250</c><c>5320363289</c></r>
 <r><c>-2741601768</c><c>5317849199</c></r>
 <r><c>-2745336675</c><c>5315157903</c></r>
 <r><c>-2749182143</c><c>5312193213</c></r>
 <r><c>-2753243687</c><c>5309303817</c></r>
 <r><c>-2758386608</c><c>5305273741</c></r>
 <r><c>-2763891380</c><c>5299726932</c></r>
 <r><c>-2769407844</c><c>5295397310</c></r>
 <r><c>-2775746743</c><c>5290644925</c></r>
 <r><c>-2780582151</c><c>5286150724</c></r>
 <r><c>-2785283280</c><c>5282119132</c></r>
 <r><c>-2789807129</c><c>5279109562</c></r>
 <r><c>-2795161413</c><c>5275710619</c></r>
 <r><c>-2799770650</c><c>5271456371</c></r>
 <r><c>-2803909163</c><c>5266873208</c></r>
 <r><c>-2808051866</c><c>5262861012</c></r>
 <r><c>-2812219625</c><c>5258457841</c></r>
 <r><c>-2816118084</c><c>5254374578</c></r>
 <r><c>-2819710378</c><c>5250833790</c></r>
 <r><c>-2823575169</c><c>5247474831</c></r>
 <r><c>-2827023762</c><c>5243812566</c></r>
</data>
</group>
